server_management/__init__.py
server_management/__main__.py
server_management/utils/__init__.py
server_management/utils/bcm.py
server_management/utils/configuration.py
server_management/utils/connections.py
server_management/utils/conversion.py
server_management/utils/execute.py
server_management/utils/file.py
starlyng_server_management-0.2.2.dist-info/METADATA
starlyng_server_management-0.2.2.dist-info/WHEEL
starlyng_server_management-0.2.2.dist-info/entry_points.txt
starlyng_server_management-0.2.2.dist-info/top_level.txt
starlyng_server_management-0.2.2.dist-info/RECORD
